odoo/addons/pos_receipt_replace_user_by_trigram/README.rst
odoo/addons/pos_receipt_replace_user_by_trigram/__init__.py
odoo/addons/pos_receipt_replace_user_by_trigram/__manifest__.py
odoo/addons/pos_receipt_replace_user_by_trigram/utils.py
odoo/addons/pos_receipt_replace_user_by_trigram/i18n/it.po
odoo/addons/pos_receipt_replace_user_by_trigram/i18n/pos_receipt_replace_user_by_trigram.pot
odoo/addons/pos_receipt_replace_user_by_trigram/models/__init__.py
odoo/addons/pos_receipt_replace_user_by_trigram/models/pos_config.py
odoo/addons/pos_receipt_replace_user_by_trigram/models/pos_session.py
odoo/addons/pos_receipt_replace_user_by_trigram/models/res_config_settings.py
odoo/addons/pos_receipt_replace_user_by_trigram/models/res_partner.py
odoo/addons/pos_receipt_replace_user_by_trigram/readme/CONFIGURE.rst
odoo/addons/pos_receipt_replace_user_by_trigram/readme/CONTRIBUTORS.rst
odoo/addons/pos_receipt_replace_user_by_trigram/readme/DESCRIPTION.rst
odoo/addons/pos_receipt_replace_user_by_trigram/static/description/icon.png
odoo/addons/pos_receipt_replace_user_by_trigram/static/description/index.html
odoo/addons/pos_receipt_replace_user_by_trigram/static/img/pos_config.png
odoo/addons/pos_receipt_replace_user_by_trigram/static/img/pos_receipt.png
odoo/addons/pos_receipt_replace_user_by_trigram/static/src/js/models.js
odoo/addons/pos_receipt_replace_user_by_trigram/static/src/js/order_receipt.js
odoo/addons/pos_receipt_replace_user_by_trigram/static/src/xml/order_receipt.xml
odoo/addons/pos_receipt_replace_user_by_trigram/tests/__init__.py
odoo/addons/pos_receipt_replace_user_by_trigram/tests/test_get_trigram.py
odoo/addons/pos_receipt_replace_user_by_trigram/views/res_config_settings.xml
odoo/addons/pos_receipt_replace_user_by_trigram/views/res_users.xml
odoo_addon_pos_receipt_replace_user_by_trigram-16.0.1.0.0.4.dist-info/METADATA
odoo_addon_pos_receipt_replace_user_by_trigram-16.0.1.0.0.4.dist-info/WHEEL
odoo_addon_pos_receipt_replace_user_by_trigram-16.0.1.0.0.4.dist-info/top_level.txt
odoo_addon_pos_receipt_replace_user_by_trigram-16.0.1.0.0.4.dist-info/RECORD
